flash_tokenizer/__init__.py
flash_tokenizer/_core.cp311-win_amd64.pyd
flash_tokenizer/batch_encoding.py
flash_tokenizer/bert_tokenizer_flash.py
flash_tokenizer/bert_tokenizer_original.py
flash_tokenizer/config.py
flash_tokenizer-1.2.0.dist-info/METADATA
flash_tokenizer-1.2.0.dist-info/WHEEL
flash_tokenizer-1.2.0.dist-info/RECORD
