Metadata-Version: 2.2
Name: flash_tokenizer
Version: 1.2.0
Summary: Extremely fast bert tokenizer
Author-Email: spring <springnode@gmail.com>
License: MIT
Classifier: Development Status :: 1 - Planning
Classifier: License :: OSI Approved :: MIT License
Classifier: Programming Language :: Python :: 3
Classifier: Programming Language :: Python :: 3.8
Classifier: Programming Language :: Python :: 3.9
Classifier: Programming Language :: Python :: 3.10
Classifier: Programming Language :: Python :: 3.11
Classifier: Programming Language :: Python :: 3.12
Classifier: Programming Language :: Python :: 3.13
Project-URL: Homepage, https://github.com/NLPOptimize/flash-tokenizer
Project-URL: Issues, https://github.com/NLPOptimize/flash-tokenizer/issues
Requires-Python: >=3.8
Requires-Dist: numpy>=1.24.0
Requires-Dist: requests
